{
  "email": "icislsloe@gmail.com",
  "name": "icic",
  "updatedAt": "2026-07-11T18:09:01Z",
  "lastWatch": {
    "imdbId": "tt29552248",
    "tmdbId": "1007757",
    "season": 1,
    "episode": 1,
    "progress": 0,
    "updatedAt": "2026-07-11T18:09:01Z"
  },
  "lastSelection": null,
  "preferences": {},
  "titles": [
    "tt29552248"
  ],
  "progress": {
    "tt29552248": {
      "imdbId": "tt29552248",
      "tmdbId": "1007757",
      "lastSeason": 1,
      "lastEpisode": 1,
      "progress": 0,
      "lastProgress": 0,
      "updatedAt": "2026-07-11T18:09:01Z"
    }
  }
}
