{
  "imdbId": "tt14850054",
  "tmdbId": "840464",
  "lastSeason": 1,
  "lastEpisode": 1,
  "progress": 0,
  "lastProgress": 0,
  "updatedAt": "2026-05-30T19:47:08Z",
  "watched": {
    "s1e1": {
      "startedAt": "2026-05-30T19:47:08Z",
      "completedAt": "",
      "lastProgress": 0
    }
  },
  "history": [
    {
      "eventId": "luzenithc1994@gmail.com:tt14850054:s1e1:preference:2026-05-30T19:47:08Z",
      "contentId": "tt14850054",
      "episodeKey": "s1e1",
      "userEmail": "luzenithc1994@gmail.com",
      "userName": "Luz Enith Campo",
      "imdbId": "tt14850054",
      "tmdbId": "840464",
      "title": "Greenland 2",
      "type": "movie",
      "season": 1,
      "episode": 1,
      "progress": 0,
      "eventType": "progress",
      "playerStatus": "preference",
      "startedAt": "",
      "completedAt": "",
      "updatedAt": "2026-05-30T19:47:08Z",
      "country": "",
      "countryName": "",
      "city": "",
      "region": "",
      "device": "",
      "browser": "",
      "locale": "",
      "timezone": ""
    }
  ]
}
