{
  "imdbId": "tt4425200",
  "tmdbId": "324552",
  "lastSeason": 1,
  "lastEpisode": 1,
  "progress": 0,
  "lastProgress": 0,
  "updatedAt": "2026-05-21T11:11:27Z",
  "watched": {},
  "history": [
    {
      "eventId": "henry8812@gmail.com:tt4425200:s1e1:started:2026-05-21T11:11:27Z",
      "contentId": "tt4425200",
      "episodeKey": "s1e1",
      "userEmail": "henry8812@gmail.com",
      "userName": "Henry Gomez",
      "imdbId": "tt4425200",
      "tmdbId": "324552",
      "title": "John Wick: Pacto de sangre",
      "type": "movie",
      "season": 1,
      "episode": 1,
      "progress": 0,
      "eventType": "started",
      "playerStatus": "playing",
      "startedAt": "2026-05-21T11:11:27.217Z",
      "completedAt": "",
      "updatedAt": "2026-05-21T11:11:27Z",
      "country": "",
      "countryName": "",
      "city": "",
      "region": "",
      "device": "",
      "browser": "",
      "locale": "",
      "timezone": ""
    }
  ]
}
